{
  "project_info": {
    "project_number": "114229310274",
    "project_id": "login-and-register-projectmad",
    "storage_bucket": "login-and-register-projectmad.appspot.com"
  },
  "client": [
    {
      "client_info": {
        "mobilesdk_app_id": "1:114229310274:android:7b7dc3e0eeb54b0bad0edb",
        "android_client_info": {
          "package_name": "com.example.projectmb_pp"
        }
      },
      "oauth_client": [],
      "api_key": [
        {
          "current_key": "AIzaSyDNM9vKIZO7lMqXZX4Zf1U78myKot1MpQ4"
        }
      ],
      "services": {
        "appinvite_service": {
          "other_platform_oauth_client": []
        }
      }
    }
  ],
  "configuration_version": "1"
}